osbee/__init__.py
osbee/osbee.py
osbee-0.3.1.dist-info/LICENSE
osbee-0.3.1.dist-info/METADATA
osbee-0.3.1.dist-info/WHEEL
osbee-0.3.1.dist-info/top_level.txt
osbee-0.3.1.dist-info/RECORD
