Metadata-Version: 2.1
Name: osbee
Version: 0.3.1
Summary: Connect to your OSBee 3-valve controller's REST API
Author-email: Allan Clark <allanc@chickenandpork.com>
License: MIT License
Project-URL: Homepage, https://github.com/chickenandpork/osbee
Project-URL: Repository, https://github.com/chickenandpork/osbee.git
Project-URL: Issues, https://github.com/chickenandpork/osbee/issues
Project-URL: Changelog, https://github.com/chickenandpork/osbee/blob/master/CHANGELOG.md
Keywords: osbee,opensprinkler
Classifier: License :: OSI Approved :: MIT License
Classifier: Programming Language :: Python
Classifier: Programming Language :: Python :: 3
License-File: LICENSE
Requires-Dist: aiohttp
Provides-Extra: dev
Requires-Dist: black; extra == "dev"
